helpfulReviewPredictor/__init__.py
helpfulReviewPredictor/best_model.pkl
helpfulReviewPredictor/predictor.py
helpfulReviewPredictor/vectorizer.pkl
helpful_review_predictor-6.dist-info/METADATA
helpful_review_predictor-6.dist-info/WHEEL
helpful_review_predictor-6.dist-info/top_level.txt
helpful_review_predictor-6.dist-info/RECORD
