Metadata-Version: 2.1
Name: helpful_review_predictor
Version: 6
Summary: Predicting helpfulness of reviews
Author: Mojtaba Maleki
Author-email: mojtaba.maleki.138022@gmail.com
Keywords: python,webdevelopment,amazon,ecommerce,online shop,review,comment,machine learning,review analysis,helpful review predictor
Classifier: Development Status :: 5 - Production/Stable
Classifier: Intended Audience :: Developers
Classifier: Intended Audience :: Education
Classifier: Intended Audience :: Science/Research
Classifier: License :: OSI Approved :: MIT License
Classifier: Programming Language :: Python :: 3
Classifier: Programming Language :: Python :: 3.7
Classifier: Programming Language :: Python :: 3.8
Classifier: Programming Language :: Python :: 3.9
Classifier: Operating System :: OS Independent
Requires-Dist: scikit-learn
Requires-Dist: numpy
Requires-Dist: scipy
Requires-Dist: joblib
Requires-Dist: textblob
